README
setup.py
python_sld.egg-info/PKG-INFO
python_sld.egg-info/SOURCES.txt
python_sld.egg-info/dependency_links.txt
python_sld.egg-info/top_level.txt
sld/__init__.py
sld/run_tests.py
sld/test/__init__.py