Metadata-Version: 1.1
Name: python-sld
Version: 1.0.7
Summary: A simple python library that enables dynamic SLD creation and manipulation.
Home-page: http://github.com/azavea/python-sld/
Author: David Zwarg
Author-email: dzwarg@azavea.com
License: Apache 2.0
Keywords: ogc sld geo geoserver mapserver osgeo
Platform: UNKNOWN
Classifier: Development Status :: 4 - Beta
Classifier: Intended Audience :: Developers
Classifier: License :: OSI Approved :: Apache Software License
Classifier: Programming Language :: Python
Classifier: Topic :: Scientific/Engineering :: GIS
Requires: lxml
